README.md
setup.py
nonebot_tsugu/__init__.py
nonebot_tsugu/api.py
nonebot_tsugu/entity.py
nonebot_tsugu/util.py
nonebot_tsugu.egg-info/PKG-INFO
nonebot_tsugu.egg-info/SOURCES.txt
nonebot_tsugu.egg-info/dependency_links.txt
nonebot_tsugu.egg-info/requires.txt
nonebot_tsugu.egg-info/top_level.txt