Metadata-Version: 2.1
Name: nonebot-tsugu
Version: 0.0.4
Summary: 基于tsugu-bangdream-bot项目实现的nonebot2插件
Home-page: https://github.com/otae-1204/NoneBot-Tsugu
Author: otae
Author-email: otae1204@qq.com
License: MIT
Classifier: Programming Language :: Python :: 3.10
Classifier: License :: OSI Approved :: MIT License
Classifier: Operating System :: OS Independent
Requires-Python: >=3.10
